commizard/__init__.py
commizard/cli.py
commizard/commands.py
commizard/config.py
commizard/git_utils.py
commizard/llm_providers.py
commizard/output.py
commizard/start.py
commizard-0.4.2.dist-info/METADATA
commizard-0.4.2.dist-info/WHEEL
commizard-0.4.2.dist-info/entry_points.txt
commizard-0.4.2.dist-info/licenses/LICENSE
commizard-0.4.2.dist-info/RECORD
