Metadata-Version: 2.4
Name: commizard
Version: 0.4.2
Summary: The commit writing Wizard Assistant
Project-URL: Homepage, https://github.com/Chungzter/CommiZard
Project-URL: Issues, https://github.com/Chungzter/CommiZard/issues
Project-URL: Changelog, https://github.com/Chungzter/CommiZard/blob/master/CHANGELOG.md
Author-email: Chungzter <freezycry@protonmail.com>
License-Expression: MIT
License-File: LICENSE
Keywords: AI assistant,Commit message helper,commit assistant,git
Classifier: Development Status :: 3 - Alpha
Classifier: Environment :: Console
Classifier: Intended Audience :: Developers
Classifier: License :: OSI Approved :: MIT License
Classifier: Operating System :: OS Independent
Classifier: Programming Language :: Python
Classifier: Programming Language :: Python :: 3
Classifier: Programming Language :: Python :: 3 :: Only
Classifier: Programming Language :: Python :: 3.9
Classifier: Programming Language :: Python :: 3.10
Classifier: Programming Language :: Python :: 3.11
Classifier: Programming Language :: Python :: 3.12
Classifier: Programming Language :: Python :: 3.13
Classifier: Programming Language :: Python :: 3.14
Classifier: Topic :: Software Development :: Version Control :: Git
Requires-Python: >=3.9
Requires-Dist: pyperclip<=1.11.0,>=1.8.0
Requires-Dist: requests<=2.32.5,>=2.32.2
Requires-Dist: rich<=14.2.0,>=13.9.0
Provides-Extra: dev
Requires-Dist: mypy<=1.19.1,>=1.0.0; extra == 'dev'
Requires-Dist: pytest-cov<=7.0.0,>=4.0.0; extra == 'dev'
Requires-Dist: pytest<=8.4.2,>=7.0.0; extra == 'dev'
Requires-Dist: ruff<=0.14.10,>=0.1.0; extra == 'dev'
